LICENSE
MANIFEST.in
README.md
setup.py
wav2bin/__version__.py
wav2bin.egg-info/PKG-INFO
wav2bin.egg-info/SOURCES.txt
wav2bin.egg-info/dependency_links.txt
wav2bin.egg-info/entry_points.txt
wav2bin.egg-info/requires.txt
wav2bin.egg-info/top_level.txt
wav2bin/imgs/App_Icon.gif
wav2bin/imgs/App_Icon.ico
wav2bin/src/__init__.py
wav2bin/src/__main__.py
wav2bin/src/draw_graph.py
wav2bin/src/graphic_interface.py
wav2bin/src/helper_functions.py
wav2bin/src/splash_screen.py