Metadata-Version: 1.2
Name: wav2bin
Version: 1.3
Summary: Program to be used concurrently with Dennis Kodimer's CEC 222 lab.
Home-page: https://github.com/jvanderen1/Kodimer_Project
Author: Joshua Van Deren
Author-email: jvanderen1@gmail.com
License: MIT
Platform: UNKNOWN
Classifier: License :: OSI Approved :: MIT License
Classifier: Programming Language :: Python :: 3 :: Only
Classifier: Natural Language :: English
Classifier: Topic :: Scientific/Engineering :: Human Machine Interfaces
Classifier: Topic :: Software Development :: User Interfaces
Requires-Python: >=3
